MANIFEST.in
setup.py
pi_ldapproxy/__init__.py
pi_ldapproxy/appcache.py
pi_ldapproxy/bindcache.py
pi_ldapproxy/config.py
pi_ldapproxy/proxy.py
pi_ldapproxy/realmmapping.py
pi_ldapproxy/usermapping.py
pi_ldapproxy/util.py
pi_ldapproxy.egg-info/PKG-INFO
pi_ldapproxy.egg-info/SOURCES.txt
pi_ldapproxy.egg-info/dependency_links.txt
pi_ldapproxy.egg-info/top_level.txt
pi_ldapproxy/test/__init__.py
pi_ldapproxy/test/mock.py
pi_ldapproxy/test/test_appcache.py
pi_ldapproxy/test/test_bindcache.py
pi_ldapproxy/test/test_failing_privacyidea.py
pi_ldapproxy/test/test_https_policy.py
pi_ldapproxy/test/test_proxy_app_cache.py
pi_ldapproxy/test/test_proxy_bind_cache.py
pi_ldapproxy/test/test_proxy_simple.py
pi_ldapproxy/test/test_proxy_user_bind.py
pi_ldapproxy/test/test_proxy_user_lookup.py
pi_ldapproxy/test/test_realmmapping.py
pi_ldapproxy/test/util.py
twisted/plugins/ldapproxy_plugin.py