Metadata-Version: 1.0
Name: pi-ldapproxy
Version: 0.6
Summary: privacyIDEA LDAP Proxy based on Twisted
Home-page: UNKNOWN
Author: UNKNOWN
Author-email: UNKNOWN
License: UNKNOWN
Platform: UNKNOWN
